napalm_ios_ad/__init__.py
napalm_ios_ad/iosad.py
napalm_ios_ad/templates/delete_ntp_peers.j2
napalm_ios_ad/templates/delete_ntp_servers.j2
napalm_ios_ad/templates/delete_snmp_config.j2
napalm_ios_ad/templates/set_hostname.j2
napalm_ios_ad/templates/set_ntp_peers.j2
napalm_ios_ad/templates/set_ntp_servers.j2
napalm_ios_ad/templates/snmp_config.j2
napalm_ios_ad/utils/textfsm_templates/ip_bgp_all_sum.tpl
napalm_ios_ad/utils/textfsm_templates/ip_bgp_neigh.tpl
napalm_ios_ad/utils/textfsm_templates/ip_bgp_neigh_afi.tpl
napalm_ios_ad/utils/textfsm_templates/show_lldp_neighbors.tpl
napalm_ios_ad/utils/textfsm_templates/show_lldp_neighbors_detail.tpl
napalm25_ios_alternative_drv-0.0.4.dist-info/LICENSE
napalm25_ios_alternative_drv-0.0.4.dist-info/METADATA
napalm25_ios_alternative_drv-0.0.4.dist-info/WHEEL
napalm25_ios_alternative_drv-0.0.4.dist-info/top_level.txt
napalm25_ios_alternative_drv-0.0.4.dist-info/RECORD
